INSTALL.txt
MANIFEST.in
README.txt
VERSION
setup.py
src/judge/__init__.py
src/judge/builtins.py
src/judge/errors.py
src/judge/meta.py
src/judge/runners.py
src/judge/util.py
src/judge/bin/__init__.py
src/judge/bin/judge.py
src/judge/graders/__init__.py
src/judge/graders/base.py
src/judge/graders/grade_io.py
src/judge/graders/util.py
src/judge/parsers/__init__.py
src/judge/parsers/io_example.py
src/judge/parsers/io_parser.py
src/judge/parsers/io_strings.py
src/judge/parsers/io_template.py
src/judge/sandbox/__init__.py
src/judge/sandbox/sandbox.py
src/pyjudge.egg-info/PKG-INFO
src/pyjudge.egg-info/SOURCES.txt
src/pyjudge.egg-info/dependency_links.txt
src/pyjudge.egg-info/entry_points.txt
src/pyjudge.egg-info/top_level.txt
src/pyjudge.egg-info/zip-safe